<annotation>
	<folder>formulaires</folder>
	<filename>p16r0upgpul7qv451hb8pk81cjh9-details.jpg</filename>
	<path>D:\Dev\yolo\dataset\images\formulaires\p16r0upgpul7qv451hb8pk81cjh9-details.jpg</path>
	<source>
		<database>Unknown</database>
	</source>
	<size>
		<width>540</width>
		<height>380</height>
		<depth>3</depth>
	</size>
	<segmented>0</segmented>
	<object>
		<name>field</name>
		<pose>Unspecified</pose>
		<truncated>0</truncated>
		<difficult>0</difficult>
		<bndbox>
			<xmin>184</xmin>
			<ymin>154</ymin>
			<xmax>370</xmax>
			<ymax>177</ymax>
		</bndbox>
	</object>
	<object>
		<name>field</name>
		<pose>Unspecified</pose>
		<truncated>0</truncated>
		<difficult>0</difficult>
		<bndbox>
			<xmin>182</xmin>
			<ymin>187</ymin>
			<xmax>369</xmax>
			<ymax>211</ymax>
		</bndbox>
	</object>
	<object>
		<name>button</name>
		<pose>Unspecified</pose>
		<truncated>0</truncated>
		<difficult>0</difficult>
		<bndbox>
			<xmin>182</xmin>
			<ymin>222</ymin>
			<xmax>370</xmax>
			<ymax>253</ymax>
		</bndbox>
	</object>
</annotation>
