<annotation>
	<folder>formulaires</folder>
	<filename>sprintly.png</filename>
	<path>D:\Dev\yolo\dataset\images\formulaires\sprintly.png</path>
	<source>
		<database>Unknown</database>
	</source>
	<size>
		<width>580</width>
		<height>556</height>
		<depth>3</depth>
	</size>
	<segmented>0</segmented>
	<object>
		<name>field</name>
		<pose>Unspecified</pose>
		<truncated>0</truncated>
		<difficult>0</difficult>
		<bndbox>
			<xmin>40</xmin>
			<ymin>156</ymin>
			<xmax>153</xmax>
			<ymax>185</ymax>
		</bndbox>
	</object>
	<object>
		<name>field</name>
		<pose>Unspecified</pose>
		<truncated>0</truncated>
		<difficult>0</difficult>
		<bndbox>
			<xmin>158</xmin>
			<ymin>157</ymin>
			<xmax>271</xmax>
			<ymax>185</ymax>
		</bndbox>
	</object>
	<object>
		<name>field</name>
		<pose>Unspecified</pose>
		<truncated>0</truncated>
		<difficult>0</difficult>
		<bndbox>
			<xmin>40</xmin>
			<ymin>191</ymin>
			<xmax>275</xmax>
			<ymax>220</ymax>
		</bndbox>
	</object>
	<object>
		<name>field</name>
		<pose>Unspecified</pose>
		<truncated>0</truncated>
		<difficult>0</difficult>
		<bndbox>
			<xmin>40</xmin>
			<ymin>226</ymin>
			<xmax>275</xmax>
			<ymax>254</ymax>
		</bndbox>
	</object>
	<object>
		<name>field</name>
		<pose>Unspecified</pose>
		<truncated>0</truncated>
		<difficult>0</difficult>
		<bndbox>
			<xmin>40</xmin>
			<ymin>262</ymin>
			<xmax>274</xmax>
			<ymax>290</ymax>
		</bndbox>
	</object>
	<object>
		<name>field</name>
		<pose>Unspecified</pose>
		<truncated>0</truncated>
		<difficult>0</difficult>
		<bndbox>
			<xmin>40</xmin>
			<ymin>296</ymin>
			<xmax>275</xmax>
			<ymax>325</ymax>
		</bndbox>
	</object>
	<object>
		<name>field</name>
		<pose>Unspecified</pose>
		<truncated>0</truncated>
		<difficult>0</difficult>
		<bndbox>
			<xmin>40</xmin>
			<ymin>385</ymin>
			<xmax>276</xmax>
			<ymax>413</ymax>
		</bndbox>
	</object>
	<object>
		<name>field</name>
		<pose>Unspecified</pose>
		<truncated>0</truncated>
		<difficult>0</difficult>
		<bndbox>
			<xmin>40</xmin>
			<ymin>419</ymin>
			<xmax>154</xmax>
			<ymax>448</ymax>
		</bndbox>
	</object>
	<object>
		<name>field</name>
		<pose>Unspecified</pose>
		<truncated>0</truncated>
		<difficult>0</difficult>
		<bndbox>
			<xmin>158</xmin>
			<ymin>420</ymin>
			<xmax>273</xmax>
			<ymax>447</ymax>
		</bndbox>
	</object>
	<object>
		<name>button</name>
		<pose>Unspecified</pose>
		<truncated>0</truncated>
		<difficult>0</difficult>
		<bndbox>
			<xmin>42</xmin>
			<ymin>467</ymin>
			<xmax>118</xmax>
			<ymax>492</ymax>
		</bndbox>
	</object>
</annotation>
